Metadata-Version: 1.2
Name: nextcloud-sdk
Version: 0.0.1
Summary: A python implementation of nextcloud API.
Home-page: UNKNOWN
Author: CookCoder
Author-email: zhangrcheng@gmail.com
License: UNKNOWN
Platform: UNKNOWN
Requires-Python: >=3.6
